odoo9_addon_external_file_location-9.0.1.0.0.99.dev14-py3.8-nspkg.pth
odoo_addons/external_file_location/README.rst
odoo_addons/external_file_location/__init__.py
odoo_addons/external_file_location/__openerp__.py
odoo_addons/external_file_location/data/cron.xml
odoo_addons/external_file_location/demo/task_demo.xml
odoo_addons/external_file_location/i18n/am.po
odoo_addons/external_file_location/i18n/ar.po
odoo_addons/external_file_location/i18n/bg.po
odoo_addons/external_file_location/i18n/bs.po
odoo_addons/external_file_location/i18n/ca.po
odoo_addons/external_file_location/i18n/ca_ES.po
odoo_addons/external_file_location/i18n/cs.po
odoo_addons/external_file_location/i18n/da.po
odoo_addons/external_file_location/i18n/de.po
odoo_addons/external_file_location/i18n/el_GR.po
odoo_addons/external_file_location/i18n/en_GB.po
odoo_addons/external_file_location/i18n/es.po
odoo_addons/external_file_location/i18n/es_AR.po
odoo_addons/external_file_location/i18n/es_CL.po
odoo_addons/external_file_location/i18n/es_CO.po
odoo_addons/external_file_location/i18n/es_CR.po
odoo_addons/external_file_location/i18n/es_DO.po
odoo_addons/external_file_location/i18n/es_EC.po
odoo_addons/external_file_location/i18n/es_ES.po
odoo_addons/external_file_location/i18n/es_MX.po
odoo_addons/external_file_location/i18n/es_PE.po
odoo_addons/external_file_location/i18n/es_PY.po
odoo_addons/external_file_location/i18n/es_VE.po
odoo_addons/external_file_location/i18n/et.po
odoo_addons/external_file_location/i18n/eu.po
odoo_addons/external_file_location/i18n/external_file_location.pot
odoo_addons/external_file_location/i18n/fa.po
odoo_addons/external_file_location/i18n/fi.po
odoo_addons/external_file_location/i18n/fr.po
odoo_addons/external_file_location/i18n/fr_CA.po
odoo_addons/external_file_location/i18n/fr_CH.po
odoo_addons/external_file_location/i18n/gl.po
odoo_addons/external_file_location/i18n/gl_ES.po
odoo_addons/external_file_location/i18n/he.po
odoo_addons/external_file_location/i18n/hr.po
odoo9_addon_external_file_location-9.0.1.0.0.99.dev14.dist-info/METADATA
odoo9_addon_external_file_location-9.0.1.0.0.99.dev14.dist-info/WHEEL
odoo9_addon_external_file_location-9.0.1.0.0.99.dev14.dist-info/namespace_packages.txt
odoo9_addon_external_file_location-9.0.1.0.0.99.dev14.dist-info/top_level.txt
odoo9_addon_external_file_location-9.0.1.0.0.99.dev14.dist-info/RECORD
